{"Message": "Ok", "ErrorCode": 1, "Response": {"bungieNetUser": {"about": "", "localeInheritDefault": true, "profilePicture": 70629, "lastUpdate": "2016-01-08T19:51:21.219Z", "showActivity": true, "showGroupMessaging": true, "profileTheme": 4, "uniqueName": "11717737", "profileThemeName": "assassin", "userTitle": 0, "userTitleDisplay": "Newbie", "displayName": "Bluesoull", "profilePicturePath": "/img/profile/avatars/bungie_day_15_42.jpg", "isDeleted": false, "membershipId": "11717737", "statusDate": "0001-01-01T00:00:00Z", "successMessageFlags": "0", "statusText": "", "psnDisplayName": "Bluesoull", "locale": "en", "firstAccess": "2015-09-17T01:27:34.88Z"}, "destinyMemberships": [{"displayName": "Bluesoull", "iconPath": "/img/theme/destiny/icons/icon_psn.png", "membershipType": 2, "membershipId": "4611686018437079666"}]}, "ErrorStatus": "Success", "ThrottleSeconds": 0, "MessageData": {}}